<?xml version="1.0"?>
<opencv_storage>
<calibration_Time>"Mon Dec  9 13:13:03 2013"</calibration_Time>
<nrOfFrames>12</nrOfFrames>
<image_Width>1440</image_Width>
<image_Height>1080</image_Height>
<board_Width>8</board_Width>
<board_Height>5</board_Height>
<square_Size>50.</square_Size>
<FixAspectRatio>1.</FixAspectRatio>
<!-- flags:  +fix_aspectRatio +fix_principal_point +zero_tangent_dist -->
<flagValue>14</flagValue>
<Camera_Matrix type_id="opencv-matrix">
  <rows>3</rows>
  <cols>3</cols>
  <dt>d</dt>
  <data>
    1.4788004986036315e+03 0. 7.1950000000000000e+02 0.
    1.4788004986036315e+03 5.3950000000000000e+02 0. 0. 1.</data></Camera_Matrix>
<Distortion_Coefficients type_id="opencv-matrix">
  <rows>5</rows>
  <cols>1</cols>
  <dt>d</dt>
  <data>
    1.6178927234579213e-01 1.0465638982122503e-01 0. 0.
    -4.3687565398471380e+00</data></Distortion_Coefficients>
<Avg_Reprojection_Error>7.1909610551903946e-01</Avg_Reprojection_Error>
<Per_View_Reprojection_Errors type_id="opencv-matrix">
  <rows>12</rows>
  <cols>1</cols>
  <dt>f</dt>
  <data>
    6.52925909e-01 7.51619995e-01 5.47328711e-01 6.46619499e-01
    7.25236893e-01 7.05167711e-01 6.49260461e-01 6.61382556e-01
    6.79567754e-01 8.64888787e-01 7.28500009e-01 9.34615850e-01</data></Per_View_Reprojection_Errors>
<!-- a set of 6-tuples (rotation vector + translation vector) for each view -->
<Extrinsic_Parameters type_id="opencv-matrix">
  <rows>12</rows>
  <cols>6</cols>
  <dt>d</dt>
  <data>
    -4.3106260992705719e-01 1.3725201084251847e-03
    -1.7594817651010376e-02 -1.9450811881384720e+02
    -4.4778115970007505e+01 1.0173690940543909e+03
    -4.3264706631454525e-01 1.7253812030883453e-01
    4.2576549395621577e-01 -1.6023777833408508e+02
    -1.8072458320335880e+02 1.0838580884508578e+03
    -4.9556054618996087e-01 -8.6076229747957797e-02
    -4.1005843202838488e-01 -2.5941285379268521e+02
    -4.6564615989502386e+01 1.0023454794115709e+03
    -7.8355159822744713e-01 6.0075252538754474e-02
    2.4421340970701803e-02 -1.9870484265871630e+02
    -9.8766967935527020e+01 1.2282663473849341e+03
    -6.5895639578604714e-01 2.8674036570504396e-01
    6.0056049529749689e-01 -1.0991512154756226e+02
    -1.9847370162620641e+02 1.1867430582281479e+03
    -6.3892108752038779e-01 4.0655603584867145e-01
    8.7862503300150252e-01 -1.6132905981313751e+01
    -1.6712839487406643e+02 1.3059774987585115e+03
    -7.4713810438012407e-01 -2.2048112112254042e-01
    -5.0800416305022289e-01 -1.2999915643806997e+02
    -1.7069363894556243e+01 1.0555996067130941e+03
    -8.7291532248816617e-01 1.1924992893767512e-02
    -6.3703465858625675e-03 -1.7355107150731851e+02
    -5.9073554615519654e+01 1.2685883452141229e+03
    -2.1383129630905925e-01 3.2340104078775751e-02
    1.7963809779161399e-01 -1.2963207022608628e+02
    -8.5276440224727537e+01 9.6354771834022756e+02
    -2.0072425733732116e-01 7.3259707798798548e-02
    -2.3574508022510099e-01 -1.6972180459071387e+02
    -6.1969676629742821e+01 9.1026709485589481e+02
    1.8401794347569075e-01 5.9076778952438978e-02 9.5259011897911462e-03
    -1.3109173826079490e+02 -5.3164541156494401e+01
    8.2558201585420511e+02 -8.6803568811537377e-02
    1.1289861742091589e-01 7.7168177093129800e-02
    -1.6250785216822899e+02 -1.0521219991151447e+02
    8.6433567827809566e+02</data></Extrinsic_Parameters>
<Image_points type_id="opencv-matrix">
  <rows>12</rows>
  <cols>40</cols>
  <dt>"2f"</dt>
  <data>
    4.34943268e+02 4.73562500e+02 5.08137146e+02 4.72594574e+02
    5.81187744e+02 4.71432800e+02 6.54212402e+02 4.71016418e+02
    7.26944763e+02 4.69403473e+02 7.99830261e+02 4.67984039e+02
    8.73218384e+02 4.66555756e+02 9.46945923e+02 4.64734558e+02
    4.30308014e+02 5.40115906e+02 5.05215302e+02 5.39531677e+02
    5.79645630e+02 5.38298218e+02 6.54049011e+02 5.36712402e+02
    7.28367126e+02 5.35772095e+02 8.02644165e+02 5.34463806e+02
    8.77400085e+02 5.33070374e+02 9.52640564e+02 5.31812378e+02
    4.26076752e+02 6.09432068e+02 5.02554260e+02 6.08519897e+02
    5.77958313e+02 6.07027039e+02 6.53987000e+02 6.05827515e+02
    7.29865479e+02 6.04452271e+02 8.05845337e+02 6.02948730e+02
    8.82275635e+02 6.01802673e+02 9.59009399e+02 6.00950745e+02
    4.20702148e+02 6.81742188e+02 4.98976410e+02 6.80545166e+02
    5.76069946e+02 6.78997192e+02 6.53833740e+02 6.77523193e+02
    7.31459961e+02 6.76115906e+02 8.09275208e+02 6.74603760e+02
    8.87319702e+02 6.73795593e+02 9.66108276e+02 6.72409363e+02
    4.15251556e+02 7.57626892e+02 4.95220520e+02 7.56008362e+02
    5.74090637e+02 7.54240845e+02 6.53743896e+02 7.52524536e+02
    7.33262817e+02 7.51080994e+02 8.12955078e+02 7.49943420e+02
    8.92949585e+02 7.49047852e+02 9.73693176e+02 7.47545837e+02
    4.99061401e+02 2.90822632e+02 5.58636108e+02 3.13351685e+02
    6.19763367e+02 3.36273010e+02 6.82680237e+02 3.60697906e+02
    7.46849609e+02 3.84169037e+02 8.12635132e+02 4.08497894e+02
    8.80483276e+02 4.33351562e+02 9.50596375e+02 4.58456421e+02
    4.64929657e+02 3.44098846e+02 5.25497131e+02 3.68344727e+02
    5.87432861e+02 3.92505035e+02 6.50587341e+02 4.16554047e+02
    7.15502930e+02 4.41867645e+02 7.81975525e+02 4.67447235e+02
    8.50422058e+02 4.93552582e+02 9.21272156e+02 5.20557922e+02
    4.30362732e+02 3.99349121e+02 4.91743744e+02 4.24503754e+02
    5.53629700e+02 4.49238678e+02 6.17724243e+02 4.74950378e+02
    6.83250977e+02 5.01076935e+02 7.50458740e+02 5.27494019e+02
    8.19567383e+02 5.55207275e+02 8.91155457e+02 5.83693909e+02
    3.93977203e+02 4.56078888e+02 4.56028595e+02 4.82150909e+02
    5.18892273e+02 5.08023712e+02 5.83546021e+02 5.34800354e+02
    6.49872498e+02 5.62108643e+02 7.17855103e+02 5.89934998e+02
    7.87773071e+02 6.19141357e+02 8.60226196e+02 6.48718567e+02
    3.56037201e+02 5.14779297e+02 4.18828827e+02 5.41779419e+02
    4.82327698e+02 5.68726624e+02 5.47880249e+02 5.96574158e+02
    6.15051086e+02 6.25246582e+02 6.84020569e+02 6.54797363e+02
    7.54838013e+02 6.85470825e+02 8.28134827e+02 7.16489990e+02
    3.32963348e+02 4.69381287e+02 4.04216492e+02 4.43672546e+02
    4.74409637e+02 4.18477814e+02 5.43287170e+02 3.94584412e+02
    6.10276794e+02 3.69779694e+02 6.76044434e+02 3.45526276e+02
    7.40823486e+02 3.21522430e+02 8.04716858e+02 2.97326233e+02
    3.55017212e+02 5.28769775e+02 4.28127777e+02 5.02822388e+02
    4.99495056e+02 4.76548828e+02 5.69219666e+02 4.50248627e+02
    6.37445618e+02 4.25136292e+02 7.04363464e+02 4.00066589e+02
    7.70131409e+02 3.75099030e+02 8.35084351e+02 3.50473938e+02
    3.78929291e+02 5.90958862e+02 4.53312195e+02 5.63386475e+02
    5.25187195e+02 5.35878601e+02 5.96300598e+02 5.08918610e+02
    6.65559814e+02 4.82297668e+02 7.33597717e+02 4.55736938e+02
    8.00672058e+02 4.30007629e+02 8.66743774e+02 4.04657898e+02
    4.02901947e+02 6.55998901e+02 4.78675995e+02 6.26864624e+02
    5.51977600e+02 5.98032227e+02 6.24256592e+02 5.69635376e+02
    6.94939148e+02 5.41703735e+02 7.64343018e+02 5.14057251e+02
    8.32554077e+02 4.87420074e+02 9.00065247e+02 4.60362183e+02
    4.27940857e+02 7.24354187e+02 5.05234436e+02 6.93375793e+02
    5.79878296e+02 6.62879883e+02 6.53685791e+02 6.32843811e+02
    7.25686279e+02 6.03560791e+02 7.96523743e+02 5.75043579e+02
    8.66209656e+02 5.47069824e+02 9.35240967e+02 5.18423462e+02
    4.79550415e+02 4.19449432e+02 5.39173706e+02 4.19409027e+02
    5.99177551e+02 4.19112732e+02 6.59571533e+02 4.19946442e+02
    7.20263489e+02 4.19192841e+02 7.81233521e+02 4.18684692e+02
    8.42830688e+02 4.17935974e+02 9.05162109e+02 4.16852631e+02
    4.69545258e+02 4.59878113e+02 5.31147644e+02 4.60899689e+02
    5.92884277e+02 4.60865753e+02 6.54974304e+02 4.60217743e+02
    7.17436890e+02 4.60457397e+02 7.80324890e+02 4.60197540e+02
    8.43621155e+02 4.59752502e+02 9.07836853e+02 4.59273865e+02
    4.59588776e+02 5.03099548e+02 5.23081543e+02 5.04005585e+02
    5.86143066e+02 5.03800415e+02 6.50216919e+02 5.04026764e+02
    7.14447693e+02 5.03782806e+02 7.79352661e+02 5.03298676e+02
    8.44651184e+02 5.03176910e+02 9.10889404e+02 5.03263123e+02
    4.48333069e+02 5.48733765e+02 5.13796448e+02 5.49648682e+02
    5.78856079e+02 5.49727600e+02 6.45010681e+02 5.49805115e+02
    7.11443848e+02 5.49780518e+02 7.78330505e+02 5.49373840e+02
    8.45741455e+02 5.49711365e+02 9.14282349e+02 5.49093140e+02
    4.36264954e+02 5.97500977e+02 5.03950684e+02 5.98180786e+02
    5.71218018e+02 5.98277771e+02 6.39499084e+02 5.98153015e+02
    7.08128235e+02 5.98263306e+02 7.77328186e+02 5.98499023e+02
    8.47176147e+02 5.98847656e+02 9.17956726e+02 5.97861877e+02
    5.81837402e+02 2.90645996e+02 6.29425842e+02 3.13439728e+02
    6.79155823e+02 3.36949707e+02 7.31073120e+02 3.62656708e+02
    7.84947510e+02 3.87577301e+02 8.41159546e+02 4.13822754e+02
    8.99979309e+02 4.41218384e+02 9.61820374e+02 4.69384369e+02
    5.40301880e+02 3.25583984e+02 5.88436829e+02 3.50654114e+02
    6.38456482e+02 3.75608398e+02 6.90413757e+02 4.00865814e+02
    7.44627686e+02 4.28171722e+02 8.01239319e+02 4.55999512e+02
    8.60425415e+02 4.84930267e+02 9.22546570e+02 5.15438660e+02
    4.97569092e+02 3.62483643e+02 5.46132629e+02 3.88544434e+02
    5.95825989e+02 4.14451050e+02 6.48392761e+02 4.41799805e+02
    7.02678406e+02 4.69991486e+02 7.59632568e+02 4.99046173e+02
    8.19164062e+02 5.29847717e+02 8.81760620e+02 5.62450439e+02
    4.52542511e+02 4.00463562e+02 5.01362793e+02 4.27801361e+02
    5.51497253e+02 4.55102417e+02 6.04173218e+02 4.83805786e+02
    6.58968872e+02 5.13604614e+02 7.16204346e+02 5.44305298e+02
    7.76182373e+02 5.77123657e+02 8.39158142e+02 6.10704041e+02
    4.05302216e+02 4.40209656e+02 4.54336121e+02 4.68584167e+02
    5.04760437e+02 4.97307953e+02 5.57772522e+02 5.27348267e+02
    6.12952026e+02 5.58661255e+02 6.70696594e+02 5.91683838e+02
    7.30934509e+02 6.26282959e+02 7.94439941e+02 6.61468628e+02
    7.00927917e+02 3.49686584e+02 7.33846191e+02 3.78716827e+02
    7.68589417e+02 4.09110443e+02 8.05272766e+02 4.42157501e+02
    8.43701538e+02 4.75317047e+02 8.84276306e+02 5.10508484e+02
    9.27255188e+02 5.47682678e+02 9.72913086e+02 5.86701416e+02
    6.54214600e+02 3.74341919e+02 6.86627380e+02 4.05313538e+02
    7.20624512e+02 4.36797241e+02 7.56430542e+02 4.69420258e+02
    7.94191895e+02 5.04580353e+02 8.33901794e+02 5.41288086e+02
    8.75888916e+02 5.79773621e+02 9.20645935e+02 6.20813721e+02
    6.06666016e+02 4.00114258e+02 6.38499207e+02 4.31797607e+02
    6.71493652e+02 4.63965851e+02 7.06561462e+02 4.98450836e+02
    7.43458313e+02 5.34382812e+02 7.82380493e+02 5.71925476e+02
    8.23517822e+02 6.12170959e+02 8.67252502e+02 6.54972656e+02
    5.57595520e+02 4.25891388e+02 5.88716248e+02 4.58677582e+02
    6.21089905e+02 4.92126221e+02 6.55346924e+02 5.27574402e+02
    6.91451965e+02 5.64830017e+02 7.29426208e+02 6.03721436e+02
    7.69584534e+02 6.45650452e+02 8.12376709e+02 6.89372986e+02
    5.07086945e+02 4.52509186e+02 5.37524841e+02 4.86205475e+02
    5.69064514e+02 5.20578857e+02 6.02510010e+02 5.57224609e+02
    6.37678589e+02 5.95681702e+02 6.74874023e+02 6.36583679e+02
    7.14100769e+02 6.79821960e+02 7.55717041e+02 7.24811890e+02
    5.37404541e+02 5.14532593e+02 5.99378662e+02 4.90419312e+02
    6.59442505e+02 4.66708832e+02 7.17527283e+02 4.45152374e+02
    7.73758301e+02 4.22483978e+02 8.28288025e+02 4.00745758e+02
    8.81513306e+02 3.79547394e+02 9.33251343e+02 3.58452240e+02
    5.69103149e+02 5.58614319e+02 6.32376953e+02 5.34176453e+02
    6.93439514e+02 5.09231842e+02 7.52629822e+02 4.84449463e+02
    8.09756104e+02 4.61510590e+02 8.65274109e+02 4.38694611e+02
    9.19368896e+02 4.16455444e+02 9.71748962e+02 3.94782898e+02
    6.03460754e+02 6.05458496e+02 6.67735474e+02 5.79006165e+02
    7.29362244e+02 5.52626953e+02 7.89623291e+02 5.27266541e+02
    8.47869934e+02 5.02286102e+02 9.04421875e+02 4.77756744e+02
    9.59538269e+02 4.54422699e+02 1.01284998e+03 4.31994507e+02
    6.39035156e+02 6.55220215e+02 7.04610535e+02 6.26857300e+02
    7.67432861e+02 5.98898926e+02 8.28784241e+02 5.71707825e+02
    8.88307922e+02 5.45386719e+02 9.46118408e+02 5.19342712e+02
    1.00197131e+03 4.94880402e+02 1.05646948e+03 4.70275482e+02
    6.77120728e+02 7.08362610e+02 7.43942688e+02 6.77637695e+02
    8.08112549e+02 6.47803955e+02 8.70921814e+02 6.18578796e+02
    9.31567200e+02 5.90481079e+02 9.90433167e+02 5.63403931e+02
    1.04747778e+03 5.37263489e+02 1.10265857e+03 5.10525543e+02
    5.17184387e+02 4.69868744e+02 5.75143494e+02 4.69425018e+02
    6.33379333e+02 4.68690094e+02 6.91616394e+02 4.69267517e+02
    7.49955933e+02 4.68132996e+02 8.08456299e+02 4.67318451e+02
    8.67389648e+02 4.66361908e+02 9.26613892e+02 4.65059387e+02
    5.10636139e+02 5.06281891e+02 5.70574097e+02 5.06780426e+02
    6.30606506e+02 5.06313141e+02 6.90705872e+02 5.05136353e+02
    7.50943909e+02 5.04959930e+02 8.11347534e+02 5.04337067e+02
    8.71941711e+02 5.03515686e+02 9.33127930e+02 5.02676605e+02
    5.04482056e+02 5.45381287e+02 5.66369690e+02 5.45588379e+02
    6.27722534e+02 5.44913696e+02 6.89783020e+02 5.44549561e+02
    7.52003845e+02 5.43814575e+02 8.14391846e+02 5.42760742e+02
    8.77066406e+02 5.42214294e+02 9.40312439e+02 5.41774109e+02
    4.97171021e+02 5.86822998e+02 5.61158020e+02 5.87101807e+02
    6.24539978e+02 5.86451355e+02 6.88846802e+02 5.85868469e+02
    7.53162659e+02 5.85241516e+02 8.17667053e+02 5.84170837e+02
    8.82501221e+02 5.83798950e+02 9.47954041e+02 5.82543579e+02
    4.89318665e+02 6.31438232e+02 5.55541687e+02 6.31284058e+02
    6.21355774e+02 6.30485596e+02 6.87832275e+02 6.29571716e+02
    7.54425415e+02 6.28758972e+02 8.21339111e+02 6.28342285e+02
    8.88515869e+02 6.27756287e+02 9.56451782e+02 6.26135986e+02
    5.18925537e+02 4.07533752e+02 5.94442688e+02 4.21134125e+02
    6.70469604e+02 4.34476135e+02 7.46779785e+02 4.48336578e+02
    8.23596191e+02 4.61403748e+02 9.01097351e+02 4.74568451e+02
    9.79540527e+02 4.88059082e+02 1.05888599e+03 5.01376831e+02
    5.02748535e+02 4.81416534e+02 5.79277039e+02 4.95423492e+02
    6.55886963e+02 5.08912750e+02 7.32918274e+02 5.22453308e+02
    8.10332703e+02 5.36266724e+02 8.88480896e+02 5.49896790e+02
    9.67554871e+02 5.63765747e+02 1.04744324e+03 5.77928040e+02
    4.87181183e+02 5.56631958e+02 5.64423279e+02 5.70585205e+02
    6.40917725e+02 5.84303894e+02 7.18812256e+02 5.98265686e+02
    7.96969971e+02 6.12285767e+02 8.75976013e+02 6.26384460e+02
    9.55789307e+02 6.40842346e+02 1.03649353e+03 6.55506531e+02
    4.70219788e+02 6.33304565e+02 5.48288696e+02 6.47330811e+02
    6.25799133e+02 6.61235718e+02 7.04452637e+02 6.75451965e+02
    7.83563782e+02 6.89780579e+02 8.63399719e+02 7.04514465e+02
    9.43967834e+02 7.19621582e+02 1.02562866e+03 7.34712097e+02
    4.52591278e+02 7.11959717e+02 5.31636292e+02 7.26015991e+02
    6.10202942e+02 7.40220337e+02 6.89838379e+02 7.54671204e+02
    7.69861328e+02 7.69530823e+02 8.50724976e+02 7.84774902e+02
    9.32234253e+02 8.00487427e+02 1.01480304e+03 8.15907410e+02
    4.41063965e+02 4.38103455e+02 5.19807556e+02 4.18730591e+02
    5.99151672e+02 3.99150330e+02 6.78975220e+02 3.79692780e+02
    7.58984924e+02 3.59198669e+02 8.39620178e+02 3.38454956e+02
    9.21496704e+02 3.17413666e+02 1.00407593e+03 2.95855286e+02
    4.57038818e+02 5.15759521e+02 5.37103394e+02 4.96634399e+02
    6.17039734e+02 4.77052307e+02 6.97284912e+02 4.56819427e+02
    7.78120605e+02 4.36788208e+02 8.59611572e+02 4.16393280e+02
    9.42359436e+02 3.95559265e+02 1.02586926e+03 3.74585236e+02
    4.74120758e+02 5.94720398e+02 5.54869690e+02 5.75375305e+02
    6.34716919e+02 5.55574219e+02 7.16070740e+02 5.35642212e+02
    7.97623840e+02 5.15565674e+02 8.80282898e+02 4.95169281e+02
    9.63874084e+02 4.74649628e+02 1.04850696e+03 4.54003693e+02
    4.90422974e+02 6.75422852e+02 5.72108154e+02 6.55576416e+02
    6.52927002e+02 6.35790039e+02 7.35081299e+02 6.15856079e+02
    8.17676819e+02 5.95764954e+02 9.01424255e+02 5.75565918e+02
    9.86133545e+02 5.55458069e+02 1.07197937e+03 5.34596558e+02
    5.06945984e+02 7.58252808e+02 5.89524475e+02 7.38067444e+02
    6.71471375e+02 7.18104004e+02 7.54663269e+02 6.97977112e+02
    8.38540833e+02 6.78008362e+02 9.23416443e+02 6.57992554e+02
    1.00933942e+03 6.38105652e+02 1.09636633e+03 6.17379333e+02
    4.84566010e+02 4.44383698e+02 5.73525452e+02 4.45466644e+02
    6.63098206e+02 4.46546936e+02 7.53454529e+02 4.47074280e+02
    8.44586548e+02 4.47745575e+02 9.37106689e+02 4.48332977e+02
    1.03112036e+03 4.49128632e+02 1.12591052e+03 4.49890717e+02
    4.86500153e+02 5.33101196e+02 5.74627502e+02 5.33936279e+02
    6.63092163e+02 5.35197876e+02 7.52292603e+02 5.36517273e+02
    8.42326050e+02 5.37391357e+02 9.33606689e+02 5.38609192e+02
    1.02643201e+03 5.39945129e+02 1.12005554e+03 5.41288635e+02
    4.89158966e+02 6.19651550e+02 5.76375977e+02 6.20528442e+02
    6.62939331e+02 6.22038513e+02 7.51273132e+02 6.23343872e+02
    8.40244507e+02 6.24975403e+02 9.30659607e+02 6.26827454e+02
    1.02243054e+03 6.28800354e+02 1.11492810e+03 6.30448547e+02
    4.90671753e+02 7.04462524e+02 5.76922668e+02 7.05400391e+02
    6.62885132e+02 7.06928833e+02 7.50265015e+02 7.08694702e+02
    8.38515503e+02 7.10688721e+02 9.28079956e+02 7.13305359e+02
    1.01866248e+03 7.15590942e+02 1.11022778e+03 7.18153381e+02
    4.92081726e+02 7.87972290e+02 5.77458069e+02 7.89167542e+02
    6.62635193e+02 7.90995544e+02 7.49407104e+02 7.93237244e+02
    8.37038025e+02 7.95664001e+02 9.25686157e+02 7.98297302e+02
    1.01527771e+03 8.01254395e+02 1.10579016e+03 8.04284180e+02
    4.38653839e+02 3.58603546e+02 5.22874695e+02 3.64181274e+02
    6.08329041e+02 3.69572876e+02 6.94841675e+02 3.75315308e+02
    7.82338501e+02 3.80228882e+02 8.71259399e+02 3.85130280e+02
    9.62111450e+02 3.90160797e+02 1.05475903e+03 3.95041138e+02
    4.30420593e+02 4.43715363e+02 5.15426392e+02 4.50021790e+02
    6.00922974e+02 4.55900635e+02 6.87372864e+02 4.61528534e+02
    7.75125000e+02 4.67404633e+02 8.64197998e+02 4.73275055e+02
    9.55251587e+02 4.79044556e+02 1.04818042e+03 4.84973450e+02
    4.22917755e+02 5.29524231e+02 5.08312500e+02 5.35850220e+02
    5.93186890e+02 5.42109741e+02 6.80078674e+02 5.48360046e+02
    7.67958313e+02 5.54859375e+02 8.57403076e+02 5.61273254e+02
    9.48607178e+02 5.68225464e+02 1.04196631e+03 5.75010559e+02
    4.14393890e+02 6.15706909e+02 4.99988403e+02 6.22393921e+02
    5.85389404e+02 6.28849670e+02 6.72540588e+02 6.35723145e+02
    7.60826965e+02 6.42786255e+02 8.50648376e+02 6.50242920e+02
    9.42367188e+02 6.57981079e+02 1.03617578e+03 6.65708923e+02
    4.05473389e+02 7.03010742e+02 4.91366760e+02 7.09796082e+02
    5.77206604e+02 7.16977356e+02 6.64829895e+02 7.24435486e+02
    7.53689819e+02 7.32192871e+02 8.44252930e+02 7.40394775e+02
    9.36378540e+02 7.49056824e+02 1.03061829e+03 7.57742065e+02</data></Image_points>
</opencv_storage>
